flask_gateway/__init__.py
flask_gateway/cli.py
flask_gateway/gateway_server.py
flask_gateway/patch.py
flask_gateway/templates/index.html
flask_gateway-0.1.0a0.dist-info/licenses/LICENSE
flask_gateway-0.1.0a0.dist-info/METADATA
flask_gateway-0.1.0a0.dist-info/WHEEL
flask_gateway-0.1.0a0.dist-info/entry_points.txt
flask_gateway-0.1.0a0.dist-info/top_level.txt
flask_gateway-0.1.0a0.dist-info/RECORD
