Metadata-Version: 2.4
Name: flask-gateway
Version: 0.1.0a0
Summary: A Flask-based reverse proxy server for routing to sub-Flask apps
Author-email: Adil Rahman <adildsw@gmail.com>
License: MIT
Project-URL: Homepage, https://github.com/adildsw/flask-gateway
Requires-Python: >=3.7
License-File: LICENSE
Requires-Dist: flask
Requires-Dist: click
Requires-Dist: requests
Dynamic: license-file
